MANIFEST.in
README.md
emoji.pth
post_setup.py
setup.cfg
setup.py
emoji_encoding.egg-info/PKG-INFO
emoji_encoding.egg-info/SOURCES.txt
emoji_encoding.egg-info/dependency_links.txt
emoji_encoding.egg-info/requires.txt
emoji_encoding.egg-info/top_level.txt
emojiencoding/__init__.py
emojiencoding/bootstrap.py
emojiencoding/emoji.py