Metadata-Version: 1.1
Name: emoji-encoding
Version: 0.0.5
Summary: Module providing Emoji encoding for Python
Home-page: https://github.com/suda/python-emoji-encoding
Author: Wojtek Siudzinski
Author-email: admin@suda.pl
License: MIT
Keywords: emoji codec encoding
Platform: UNKNOWN
Classifier: Development Status :: 3 - Alpha
Classifier: Intended Audience :: Developers
Classifier: Topic :: Software Development :: Build Tools
Classifier: License :: OSI Approved :: MIT License
Classifier: Programming Language :: Python :: 2
Classifier: Programming Language :: Python :: 2.6
Classifier: Programming Language :: Python :: 2.7
Classifier: Programming Language :: Python :: 3
Classifier: Programming Language :: Python :: 3.2
Classifier: Programming Language :: Python :: 3.3
Classifier: Programming Language :: Python :: 3.4
Classifier: Programming Language :: Python :: 3.5
